nish_lotto/__init__.py
nish_lotto/draw.py
nish_lotto-0.2.0.dist-info/METADATA
nish_lotto-0.2.0.dist-info/WHEEL
nish_lotto-0.2.0.dist-info/top_level.txt
nish_lotto-0.2.0.dist-info/RECORD
